dplearn/__init__.py
dplearn/data_sample.py
dplearn/extra.py
dplearn/math.py
dplearn/quant.py
dplearn/tools.py
dplearn/data/kLine.csv
dplearn-2.2.2.dist-info/LICENSE
dplearn-2.2.2.dist-info/METADATA
dplearn-2.2.2.dist-info/WHEEL
dplearn-2.2.2.dist-info/top_level.txt
dplearn-2.2.2.dist-info/RECORD
