Metadata-Version: 2.1
Name: dplearn
Version: 2.2.2
Summary: An useful package for data analysis. 
Home-page: https://github.com/Dual-Points/dplearn
Author: Sen LEI
Author-email: sen.lei@outlook.com
License: BSD 3-clause
Keywords: deep-learning,data-mining,data-tools,statistical-modeling,data-analysis,data-science
Platform: UNKNOWN
Classifier: Development Status :: 3 - Alpha
Classifier: Programming Language :: Python :: 3.8
Classifier: License :: OSI Approved :: BSD License
Classifier: Operating System :: OS Independent
License-File: LICENSE
